tyro_strict/__init__.py
tyro_strict/strict_cli.py
tyro_strict-0.1.0.dist-info/LICENSE
tyro_strict-0.1.0.dist-info/METADATA
tyro_strict-0.1.0.dist-info/WHEEL
tyro_strict-0.1.0.dist-info/RECORD
