Metadata-Version: 2.1
Name: tyro-strict
Version: 0.1.0
Summary: 
Author: Sander Teunissen
Author-email: s.teunissen@gmail.com
Requires-Python: >=3.10,<4.0
Classifier: Programming Language :: Python :: 3
Classifier: Programming Language :: Python :: 3.10
Classifier: Programming Language :: Python :: 3.11
Requires-Dist: pydantic (>=2)
Requires-Dist: tyro (>=0.5.7)
